airflow/providers/apache/impala/__init__.py
airflow/providers/apache/impala/get_provider_info.py
airflow/providers/apache/impala/version_compat.py
airflow/providers/apache/impala/hooks/__init__.py
airflow/providers/apache/impala/hooks/impala.py
apache_airflow_providers_apache_impala-1.8.1.dist-info/entry_points.txt
apache_airflow_providers_apache_impala-1.8.1.dist-info/licenses/LICENSE
apache_airflow_providers_apache_impala-1.8.1.dist-info/licenses/NOTICE
apache_airflow_providers_apache_impala-1.8.1.dist-info/WHEEL
apache_airflow_providers_apache_impala-1.8.1.dist-info/METADATA
apache_airflow_providers_apache_impala-1.8.1.dist-info/RECORD
