Metadata-Version: 2.4
Name: apache-airflow-providers-apache-impala
Version: 1.8.1
Summary: Provider package apache-airflow-providers-apache-impala for Apache Airflow
Keywords: airflow-provider,apache.impala,airflow,integration
Author-email: Apache Software Foundation <dev@airflow.apache.org>
Maintainer-email: Apache Software Foundation <dev@airflow.apache.org>
Requires-Python: >=3.10
License-Expression: Apache-2.0
Classifier: Development Status :: 5 - Production/Stable
Classifier: Environment :: Console
Classifier: Environment :: Web Environment
Classifier: Intended Audience :: Developers
Classifier: Intended Audience :: System Administrators
Classifier: Framework :: Apache Airflow
Classifier: Framework :: Apache Airflow :: Provider
Classifier: Programming Language :: Python :: 3.10
Classifier: Programming Language :: Python :: 3.11
Classifier: Programming Language :: Python :: 3.12
Classifier: Programming Language :: Python :: 3.13
Classifier: Topic :: System :: Monitoring
License-File: LICENSE
License-File: NOTICE
Requires-Dist: impyla>=0.22.0,<1.0
Requires-Dist: apache-airflow-providers-common-compat>=1.12.0
Requires-Dist: apache-airflow-providers-common-sql>=1.26.0
Requires-Dist: apache-airflow>=2.11.0
Requires-Dist: kerberos>=1.3.0 ; extra == "kerberos"
Requires-Dist: sqlalchemy>=1.4.49 ; extra == "sqlalchemy"
Project-URL: Bug Tracker, https://github.com/apache/airflow/issues
Project-URL: Changelog, https://airflow.apache.org/docs/apache-airflow-providers-apache-impala/1.8.1/changelog.html
Project-URL: Documentation, https://airflow.apache.org/docs/apache-airflow-providers-apache-impala/1.8.1
Project-URL: Mastodon, https://fosstodon.org/@airflow
Project-URL: Slack Chat, https://s.apache.org/airflow-slack
Project-URL: Source Code, https://github.com/apache/airflow
Project-URL: YouTube, https://www.youtube.com/channel/UCSXwxpWZQ7XZ1WL3wqevChA/
Provides-Extra: kerberos
Provides-Extra: sqlalchemy
